[{"印记": "", "題跋類別": "題跋", "作者": "清高宗", "位置": "本幅", "款識": "", "書體": "行書", "全文": "蘇軾東坡。"}, {"印记": "", "題跋類別": "題跋", "作者": "清高宗", "位置": "本幅", "款識": "", "書體": "行書", "全文": "蔡肇天啟。"}, {"印记": "", "題跋類別": "題跋", "作者": "清高宗", "位置": "本幅", "款識": "", "書體": "行書", "全文": "李之儀端叔。"}, {"印记": "", "題跋類別": "題跋", "作者": "清高宗", "位置": "本幅", "款識": "", "書體": "行書", "全文": "王詵晉卿。"}, {"印记": "", "題跋類別": "題跋", "作者": "清高宗", "位置": "本幅", "款識": "", "書體": "行書", "全文": "秦觀少游。"}, {"印记": "", "題跋類別": "題跋", "作者": "清高宗", "位置": "本幅", "款識": "", "書體": "行書", "全文": "道士陳碧虛。"}, {"印记": "", "題跋類別": "題跋", "作者": "清高宗", "位置": "本幅", "款識": "", "書體": "行書", "全文": "李公麟伯時。"}, {"印记": "", "題跋類別": "題跋", "作者": "清高宗", "位置": "本幅", "款識": "", "書體": "行書", "全文": "蘇轍子由。"}, {"印记": "", "題跋類別": "題跋", "作者": "清高宗", "位置": "本幅", "款識": "", "書體": "行書", "全文": "張耒文潛。"}, {"印记": "", "題跋類別": "題跋", "作者": "清高宗", "位置": "本幅", "款識": "", "書體": "行書", "全文": "黃庭堅魯直。"}, {"印记": "", "題跋類別": "題跋", "作者": "清高宗", "位置": "本幅", "款識": "", "書體": "行書", "全文": "晁補之无咎。"}, {"印记": "", "題跋類別": "題跋", "作者": "清高宗", "位置": "本幅", "款識": "", "書體": "行書", "全文": "鄭靖老。"}, {"印记": "", "題跋類別": "題跋", "作者": "清高宗", "位置": "本幅", "款識": "", "書體": "行書", "全文": "米芾元章。"}, {"印记": "", "題跋類別": "題跋", "作者": "清高宗", "位置": "本幅", "款識": "", "書體": "行書", "全文": "王欽臣仲至。"}, {"印记": "", "題跋類別": "題跋", "作者": "清高宗", "位置": "本幅", "款識": "", "書體": "行書", "全文": "劉涇巨濟。"}, {"印记": "", "題跋類別": "題跋", "作者": "清高宗", "位置": "本幅", "款識": "", "書體": "行書", "全文": "僧曇秀圓通大師。"}, {"印记": "", "題跋類別": "題跋", "作者": "清高宗", "位置": "本幅", "款識": "乾隆丁未（西元一七八七年）清和上澣御題。", "書體": "行書", "全文": "公麟然否實公麟。古筆知誠出宋人。跋語奚妨去其贋。長圖益足尚斯真。衣衫如篆渾唐法。蕉石生神異李皴。名欵設惟徵故紙。是為求劍刻舟倫。乾隆丁未（西元一七八七年）清和上澣御題。"}, {"印记": "", "題跋類別": "題跋", "作者": "董誥", "位置": "本幅", "款識": "乾隆丁未（西元一七八七年）清和月。臣董誥奉敕敬書。", "書體": "楷書", "全文": "右卷續入石渠。舊題為李公麟西園勝會圖。幾暇重加披覽。見其佈景古茂。雖用公麟之事。而畫法則全異公麟蹊徑。因命内廷翰臣等。以米芾西園雅集圖記校之。其人數位置皆合。惟第二第三叚敘次前後不同。盖文章畫趣各適其適。固自無妨也。至用筆蒼秀雄渾。生動開張。人物衣褶有古篆籀遺意。與公麟所畫用筆不類。雖幀中無款自屬宋名家手筆。正不藉假託龍眠以增聲價耳。幀後不知何人捨記而别作識語。且記中十六人僅止十一。又訛李端叔為李公擇。僧曇秀為道潛。甚至兩見東坡。三見王銑。又訛詵作侁。舛謬蕪雜之處。不值一噱。盖陋者偶得是卷。妄為綴識。不自知其蛇足也。爰命截去題跋。改題宋人西園雅集圖籖。以存真面。既於圖中諸人親書其名。並識如右。乾隆丁未（西元一七八七年）清和月。臣董誥奉勅敬書。"}]