[{"印记": "", "題跋類別": "題跋", "作者": "米芾", "位置": "拖尾", "款識": "崇寧歲在壬午五月二日。襄陽米芾書。", "書體": "行書", "全文": "畫以人物花竹鳥獸禽蟲為神妙。宮室臺榭園池器用為精巧。獨山水清雄奇富。變態無窮為難。王公之筆。渾然天成。燦然日新。已離畫工之度數。而得詩人之清麗也。崇寧歲在壬午五月二日。襄陽米芾書。"}, {"印记": "", "題跋類別": "題跋", "作者": "李孝彥", "位置": "拖尾", "款識": "政和三年秋八月既望（原書倒置）。濮陽李孝彥晉陵吳繼同觀。", "書體": "楷書", "全文": ""}, {"印记": "", "題跋類別": "題跋", "作者": "賈洵", "位置": "拖尾", "款識": "政和丙申臘月二日。賈洵題。", "書體": "行書", "全文": "右山陰圖。王右丞筆也。圖中四像。為許玄度。王逸少。謝安石。支道林。其風流可想見。右丞作此。其亦有景慕之心哉。政和丙申臘月二日。賈洵題。"}, {"印记": "", "題跋類別": "題跋", "作者": "盧襄", "位置": "拖尾", "款識": "贊元仲藏似矩。同觀於寬夫芝房。癸卯五月二十七日。", "書體": "楷書", "全文": ""}, {"印记": "", "題跋類別": "題跋", "作者": "董其昌", "位置": "拖尾", "款識": "董其昌題", "書體": "行書", "全文": "王右丞山陰高會圖。五代時陸瑾皆祖之。宋僧道潛題詞。止謝安王羲之與山陰道士支公四人耳。此卷題者。加許玄度稍異。觀其畫法。所謂雲峰石色。迥出天機。筆意縱橫。參乎造化者。不虛也。米海岳數行押。尤有獻之法。董其昌題。"}, {"印记": "", "題跋類別": "題跋", "作者": "", "位置": "前隔水", "款識": "", "書體": "楷書", "全文": "唐王維山陰圖"}]