[{"印记": "", "題跋類別": "題跋", "作者": "錢選", "位置": "本幅", "款識": "吳興錢選舜舉", "書體": "楷書", "全文": "周昉當年號神品。能傳宮禁眾名姬。因看雙陸思纖手。想見唐家極盛時。吳興錢選舜舉。"}, {"印记": "", "題跋類別": "題跋", "作者": "劉孝基", "位置": "拖尾", "款識": "劉孝基題", "書體": "楷書", "全文": "睡起深宮未梳沐。供湯侍婢走匍匐。女工不親無用心。髼髟丐雙雙打雙陸。劉孝基題。"}, {"印记": "", "題跋類別": "題跋", "作者": "陸師道", "位置": "拖尾", "款識": "五湖陸師道", "書體": "楷書", "全文": "嘉靖壬戌二月十日。偶偕尚之。磬室。過王氏園亭。得者見此圖。乃唐人周昉筆也。而錢進士為之題。設色精雅。神妙絕倫。如良工之無斧鑿痕。視之皆有生意。真超凡入聖之筆也。季重不知何緣得此。余把玩久之。因附題云。曉來嬾去褪殘米庄。且戲樗蒲賭勝忙。豈為日長無箇事。故尋消遣在昭陽。五湖陸師道。"}, {"印记": "", "題跋類別": "題籤", "作者": "清高宗", "位置": "", "款識": "", "書體": "", "全文": "周昉內人雙陸圖"}]